{"chapter": 552, "type": "color", "pageCount": 104, "arc": "Lookism", "saga": "Lookism", "pages": [{"n": 1, "w": 1080, "h": 2735}, {"n": 2, "w": 1080, "h": 2015}, {"n": 3, "w": 1080, "h": 2015}, {"n": 4, "w": 1080, "h": 1883}, {"n": 5, "w": 1080, "h": 2014}, {"n": 6, "w": 1080, "h": 4628}, {"n": 7, "w": 1080, "h": 4628}, {"n": 8, "w": 1080, "h": 3478}, {"n": 9, "w": 1080, "h": 3477}, {"n": 10, "w": 1080, "h": 4096}, {"n": 11, "w": 1080, "h": 4096}, {"n": 12, "w": 1080, "h": 2300}, {"n": 13, "w": 1080, "h": 2300}, {"n": 14, "w": 1080, "h": 2300}, {"n": 15, "w": 1080, "h": 2300}, {"n": 16, "w": 1080, "h": 3662}, {"n": 17, "w": 1080, "h": 3662}, {"n": 18, "w": 1080, "h": 2149}, {"n": 19, "w": 1080, "h": 2148}, {"n": 20, "w": 1080, "h": 2148}, {"n": 21, "w": 1080, "h": 2148}, {"n": 22, "w": 1080, "h": 2148}, {"n": 23, "w": 1080, "h": 4295}, {"n": 24, "w": 1080, "h": 4295}, {"n": 25, "w": 1080, "h": 2068}, {"n": 26, "w": 1080, "h": 2068}, {"n": 27, "w": 1080, "h": 2067}, {"n": 28, "w": 1080, "h": 2067}, {"n": 29, "w": 1080, "h": 2067}, {"n": 30, "w": 1080, "h": 5995}, {"n": 31, "w": 1080, "h": 5995}, {"n": 32, "w": 1080, "h": 2490}, {"n": 33, "w": 1080, "h": 2490}, {"n": 34, "w": 1080, "h": 2490}, {"n": 35, "w": 1080, "h": 2490}, {"n": 36, "w": 1080, "h": 2489}, {"n": 37, "w": 1080, "h": 4580}, {"n": 38, "w": 1080, "h": 3904}, {"n": 39, "w": 1080, "h": 2508}, {"n": 40, "w": 1080, "h": 2507}, {"n": 41, "w": 1080, "h": 2507}, {"n": 42, "w": 1080, "h": 2215}, {"n": 43, "w": 1080, "h": 2214}, {"n": 44, "w": 1080, "h": 2214}, {"n": 45, "w": 1080, "h": 2214}, {"n": 46, "w": 1080, "h": 2577}, {"n": 47, "w": 1080, "h": 2577}, {"n": 48, "w": 1080, "h": 2577}, {"n": 49, "w": 1080, "h": 2576}, {"n": 50, "w": 1080, "h": 2576}, {"n": 51, "w": 1080, "h": 4707}, {"n": 52, "w": 1080, "h": 4707}, {"n": 53, "w": 1080, "h": 2063}, {"n": 54, "w": 1080, "h": 2063}, {"n": 55, "w": 1080, "h": 2063}, {"n": 56, "w": 1080, "h": 2063}, {"n": 57, "w": 1080, "h": 2062}, {"n": 58, "w": 1080, "h": 5448}, {"n": 59, "w": 1080, "h": 5448}, {"n": 60, "w": 1080, "h": 2082}, {"n": 61, "w": 1080, "h": 2082}, {"n": 62, "w": 1080, "h": 2082}, {"n": 63, "w": 1080, "h": 2081}, {"n": 64, "w": 1080, "h": 4778}, {"n": 65, "w": 1080, "h": 4778}, {"n": 66, "w": 1080, "h": 2148}, {"n": 67, "w": 1080, "h": 2147}, {"n": 68, "w": 1080, "h": 2147}, {"n": 69, "w": 1080, "h": 2309}, {"n": 70, "w": 1080, "h": 2309}, {"n": 71, "w": 1080, "h": 2309}, {"n": 72, "w": 1080, "h": 2308}, {"n": 73, "w": 1080, "h": 2191}, {"n": 74, "w": 1080, "h": 2191}, {"n": 75, "w": 1080, "h": 2191}, {"n": 76, "w": 1080, "h": 2190}, {"n": 77, "w": 1080, "h": 2190}, {"n": 78, "w": 1080, "h": 2639}, {"n": 79, "w": 1080, "h": 2639}, {"n": 80, "w": 1080, "h": 2638}, {"n": 81, "w": 1080, "h": 3523}, {"n": 82, "w": 1080, "h": 3523}, {"n": 83, "w": 1080, "h": 3414}, {"n": 84, "w": 1080, "h": 3414}, {"n": 85, "w": 1080, "h": 4015}, {"n": 86, "w": 1080, "h": 4015}, {"n": 87, "w": 1080, "h": 6111}, {"n": 88, "w": 1080, "h": 6111}, {"n": 89, "w": 1080, "h": 5330}, {"n": 90, "w": 1080, "h": 5083}, {"n": 91, "w": 1080, "h": 5614}, {"n": 92, "w": 1080, "h": 5614}, {"n": 93, "w": 1080, "h": 4496}, {"n": 94, "w": 1080, "h": 4496}, {"n": 95, "w": 1080, "h": 5205}, {"n": 96, "w": 1080, "h": 5205}, {"n": 97, "w": 1080, "h": 3762}, {"n": 98, "w": 1080, "h": 3762}, {"n": 99, "w": 1080, "h": 4442}, {"n": 100, "w": 1080, "h": 4442}, {"n": 101, "w": 1080, "h": 4246}, {"n": 102, "w": 1080, "h": 4246}, {"n": 103, "w": 1080, "h": 5657}, {"n": 104, "w": 1080, "h": 5657}]}