{"chapter": 5, "type": "color", "pageCount": 22, "arc": "Getsuyoubi No Tawawa Twitter Webcomic", "saga": "Getsuyoubi No Tawawa Twitter Webcomic", "pages": [{"n": 1, "w": 1080, "h": 1565}, {"n": 2, "w": 1080, "h": 1569}, {"n": 3, "w": 1080, "h": 1579}, {"n": 4, "w": 1080, "h": 1569}, {"n": 5, "w": 1080, "h": 1569}, {"n": 6, "w": 1080, "h": 1569}, {"n": 7, "w": 1080, "h": 1569}, {"n": 8, "w": 1080, "h": 1569}, {"n": 9, "w": 1080, "h": 1569}, {"n": 10, "w": 1080, "h": 1584}, {"n": 11, "w": 1080, "h": 1627}, {"n": 12, "w": 1080, "h": 1610}, {"n": 13, "w": 1080, "h": 1607}, {"n": 14, "w": 1080, "h": 1569}, {"n": 15, "w": 1080, "h": 1582}, {"n": 16, "w": 1080, "h": 1575}, {"n": 17, "w": 1080, "h": 1575}, {"n": 18, "w": 1080, "h": 1576}, {"n": 19, "w": 1080, "h": 1577}, {"n": 20, "w": 1080, "h": 1543}, {"n": 21, "w": 1080, "h": 1577}, {"n": 22, "w": 1080, "h": 1579}]}